{
  "connection": "default",
  "collectionName": "section",
  "info": {
    "name": "section",
    "description": ""
  },
  "options": {
    "timestamps": true
  },
  "attributes": {
    "section": {
      "type": "string"
    },
    "title": {
      "type": "string"
    },
    "icon": {
      "model": "file",
      "via": "related",
      "plugin": "upload"
    },
    "subTitle": {
      "type": "string"
    },
    "order": {
      "type": "integer"
    },
    "body": {
      "type": "text"
    },
    "paths": {
      "type": "json"
    }
  }
}